<?xml version="1.0" encoding="UTF-8"?>
<objects serializationModel="Studio.02.02.00">
	<object class="EffectPreset" id="{7bae5eca-0f4c-443f-872f-38415133a007}">
		<property name="name">
			<value>VoiceLineEffects</value>
		</property>
		<relationship name="folder">
			<destination>{9ead80a4-4e1c-4a81-bb01-c6ff6c88cbfa}</destination>
		</relationship>
		<relationship name="effect">
			<destination>{3df9ab68-0b17-4d63-a1ba-9816840f8c4d}</destination>
		</relationship>
	</object>
	<object class="EffectChain" id="{3df9ab68-0b17-4d63-a1ba-9816840f8c4d}">
		<relationship name="effects">
			<destination>{7ed37b6c-0af9-4f10-a1b5-8c23303baa26}</destination>
			<destination>{4cc3da45-479f-4d90-affc-78be220e103e}</destination>
			<destination>{6efde223-5718-4063-8820-a5111e4ceb60}</destination>
			<destination>{3ebfcd41-b857-4fb1-860e-e067c2620abf}</destination>
			<destination>{9dd3036e-ae76-4f48-bb23-c07600a847bc}</destination>
		</relationship>
	</object>
	<object class="ChorusEffect" id="{7ed37b6c-0af9-4f10-a1b5-8c23303baa26}">
		<property name="rate">
			<value>0.479999989</value>
		</property>
		<property name="depth">
			<value>37.5</value>
		</property>
		<property name="mix">
			<value>81</value>
		</property>
	</object>
	<object class="DelayEffect" id="{4cc3da45-479f-4d90-affc-78be220e103e}">
		<property name="delay">
			<value>8.60000038</value>
		</property>
		<property name="level">
			<value>-5.5</value>
		</property>
	</object>
	<object class="PitchShifterEffect" id="{6efde223-5718-4063-8820-a5111e4ceb60}">
		<property name="pitch">
			<value>1.12</value>
		</property>
		<property name="fftSize">
			<value>2800</value>
		</property>
		<property name="overlap">
			<value>12.6000004</value>
		</property>
		<property name="maxChannels">
			<value>8.80000019</value>
		</property>
	</object>
	<object class="ThreeEQEffect" id="{3ebfcd41-b857-4fb1-860e-e067c2620abf}">
		<property name="lowGain">
			<value>-5</value>
		</property>
		<property name="midGain">
			<value>2.5</value>
		</property>
		<property name="crossoverSlope">
			<value>0</value>
		</property>
	</object>
	<object class="LimiterEffect" id="{9dd3036e-ae76-4f48-bb23-c07600a847bc}">
		<property name="boost">
			<value>6.4000001</value>
		</property>
	</object>
</objects>
